deveta/__init__.py
deveta/kary.py
deveta/locate.py
deveta/stream/__init__.py
deveta/stream/ansi_colors.py
deveta/stream/stdout.py
deveta-2.0.1.dist-info/LICENSE
deveta-2.0.1.dist-info/METADATA
deveta-2.0.1.dist-info/WHEEL
deveta-2.0.1.dist-info/top_level.txt
deveta-2.0.1.dist-info/RECORD
