Metadata-Version: 2.1
Name: deveta
Version: 2.0.1
Summary: A python library that collects potentially useful code-blocks
Home-page: https://github.com/comrumino/deveta
Author: James Stronz
Author-email: comrumino@archstrike.org
License: GPLv3
Platform: UNKNOWN
